{
  "book": "JST Mark",
  "chapter": 4,
  "reference": "JST Mark 4",
  "verses": [
    {
      "verse": 1,
      "reference": "JST Mark 4:1",
      "text": "And he began again to teach by the **seaside;** and there was gathered unto him a great multitude, so that he entered into a **ship** and sat in the sea; and the whole multitude was by the sea on the land."
    },
    {
      "verse": 2,
      "reference": "JST Mark 4:2",
      "text": "And he taught them many things by **parables.**"
    },
    {
      "verse": 3,
      "reference": "JST Mark 4:3",
      "text": "And he said unto them in his doctrine, Hearken; **behold,** there went out a sower to **sow;**"
    },
    {
      "verse": 4,
      "reference": "JST Mark 4:4",
      "text": "And it came to **pass** as he sowed, some fell by the **wayside,** and the fowls of the air came and devoured it up."
    },
    {
      "verse": 5,
      "reference": "JST Mark 4:5",
      "text": "And some fell on stony ground, where it had not much earth; and immediately it sprang **up** because it had no depth of **earth;** **but** when the sun was up, it was scorched; and because it had no root, it withered away."
    },
    {
      "verse": 6,
      "reference": "JST Mark 4:6",
      "text": "And some fell among thorns, and the thorns grew **up** and choked **it;** and it yielded no fruit."
    },
    {
      "verse": 7,
      "reference": "JST Mark 4:7",
      "text": "And other {{seed}} fell on good ground, and did yield fruit that sprang **up,** and **increased,** and brought forth, some **thirtyfold,** some sixty, and some **a** hundred."
    },
    {
      "verse": 8,
      "reference": "JST Mark 4:8",
      "text": "And he said unto them, He that hath ears to hear, let him hear."
    },
    {
      "verse": 9,
      "reference": "JST Mark 4:9",
      "text": "And when he was {{alone}} {{with}} {{the}} {{twelve}} {{and}} {{they}} {{that}} {{believed}} {{in}} {{him,}} they that were about him with the twelve asked of him the parable."
    },
    {
      "verse": 10,
      "reference": "JST Mark 4:10",
      "text": "And he said unto them, Unto you it is given to know the mystery of the kingdom of **God;** but unto them that are without, all things are done in **parables,**"
    },
    {
      "verse": 11,
      "reference": "JST Mark 4:11",
      "text": "That **seeing,** they may **see** and not perceive; and **hearing,** they may **hear** and not understand; lest at any time they should be **converted** and their sins should be forgiven them."
    },
    {
      "verse": 12,
      "reference": "JST Mark 4:12",
      "text": "And he said unto them, Know ye not this parable? **And** how then will ye know all parables?"
    },
    {
      "verse": 13,
      "reference": "JST Mark 4:13",
      "text": "The sower soweth the word."
    },
    {
      "verse": 14,
      "reference": "JST Mark 4:14",
      "text": "And these are they by the **wayside,** where the word is sown; but when they have heard, Satan cometh **immediately** and taketh away the word that was sown in their hearts."
    },
    {
      "verse": 15,
      "reference": "JST Mark 4:15",
      "text": "And these are they likewise which {{receive}} {{the}} {{word}} on stony **ground,** who, when they have heard the word, immediately receive it with **gladness,** **and** have no root in themselves, and so endure but for a {{time;}} {{and}} afterward, when affliction or persecution ariseth for the word's sake, immediately they are offended."
    },
    {
      "verse": 16,
      "reference": "JST Mark 4:16",
      "text": "And these are they {{who}} {{receive}} {{the}} {{word}} among **thorns,** such as hear the word, **and** the cares of this world, and the deceitfulness of riches, and the lusts of other things entering **in** choke the **word;** and it becometh unfruitful."
    },
    {
      "verse": 17,
      "reference": "JST Mark 4:17",
      "text": "And these are they {{who}} {{receive}} {{the}} {{word}} on good **ground,** such as hear the word, and receive it, and bring forth fruit, some thirtyfold, some sixty, and some **a** hundred."
    },
    {
      "verse": 18,
      "reference": "JST Mark 4:18",
      "text": "And he said unto them, Is a candle brought to be put under a bushel, or under a **bed,** and not to be set on a candlestick? {{I say unto you, Nay;}}"
    },
    {
      "verse": 19,
      "reference": "JST Mark 4:19",
      "text": "For there is nothing **hid** which shall not be manifested; neither was **anything** kept secret, but that it should {{in due time}} come abroad. If any man have ears to hear, let him hear."
    },
    {
      "verse": 20,
      "reference": "JST Mark 4:20",
      "text": "And he said unto them, Take heed what ye {{hear;}} {{for}} with what measure ye mete, it shall be measured to **you;** and unto you that {{continue}} {{to}} {{receive,}} shall more be **given;** **for** he that {{receiveth,}} to him shall be **given;** **but** he that {{continueth}} {{not}} {{to}} {{receive,}} from him shall be taken even that which he hath."
    },
    {
      "verse": 21,
      "reference": "JST Mark 4:21",
      "text": "And he said, So is the kingdom of **God;** as if a man should cast seed into the **ground,** **and** should **sleep** and **rise,** night and day, and the seed should spring and grow up, he knoweth not **how;**"
    },
    {
      "verse": 22,
      "reference": "JST Mark 4:22",
      "text": "For the earth bringeth forth fruit of **herself:** first the blade, then the ear, after that the full corn in the ear."
    },
    {
      "verse": 23,
      "reference": "JST Mark 4:23",
      "text": "But when the fruit is brought forth, immediately he putteth in the **sickle** because the harvest is come."
    },
    {
      "verse": 24,
      "reference": "JST Mark 4:24",
      "text": "And he said, Whereunto shall {{I}} liken the kingdom of God? **Or** with what comparison shall we compare it?"
    },
    {
      "verse": 25,
      "reference": "JST Mark 4:25",
      "text": "It is like a grain of mustard seed, which, when it is sown in the earth, is less than all the seeds that be in the **earth;** **but** when it is sown, it groweth up, and becometh greater than all herbs, and shooteth out great **branches,** so that the fowls of the air may lodge under the shadow of it."
    },
    {
      "verse": 26,
      "reference": "JST Mark 4:26",
      "text": "And with many such parables spake he the word unto them, as they were able to **bear;** **but** without a parable spake he not unto {{them.}}"
    },
    {
      "verse": 27,
      "reference": "JST Mark 4:27",
      "text": "{{And}} when they were alone, he expounded all things **unto** his disciples."
    },
    {
      "verse": 28,
      "reference": "JST Mark 4:28",
      "text": "And the same day, when the even was come, he **said** unto them, Let us pass over unto the other side."
    },
    {
      "verse": 29,
      "reference": "JST Mark 4:29",
      "text": "And when they had sent away the multitude, they took **him,** even as he **was,** in the ship. And there were also with him other little ships."
    },
    {
      "verse": 30,
      "reference": "JST Mark 4:30",
      "text": "And there arose a great storm of wind, and the waves beat {{over}} into the {{ship;}} {{and}} he was in the hinder part of the **ship** asleep on a **pillow;** and they **awoke** **him** and **said** unto him, Master, carest thou not that we perish?"
    },
    {
      "verse": 31,
      "reference": "JST Mark 4:31",
      "text": "And he arose, and rebuked the wind, and said unto the sea, **Peace;** be **still;** **and** the wind ceased, and there was a great calm."
    },
    {
      "verse": 32,
      "reference": "JST Mark 4:32",
      "text": "And he said unto them, Why are ye so fearful? **How** is it that ye have no faith?"
    },
    {
      "verse": 33,
      "reference": "JST Mark 4:33",
      "text": "And they feared **exceedingly** and said one to another, What manner of man is this, that even the wind and the sea obey him?"
    }
  ]
}